AUTHORS.rst
CONTRIBUTING.rst
HISTORY.rst
MANIFEST.in
README.rst
setup.cfg
setup.py
docs/Makefile
docs/authors.rst
docs/conf.py
docs/contributing.rst
docs/history.rst
docs/index.rst
docs/installation.rst
docs/make.bat
docs/readme.rst
docs/usage.rst
rage4/__init__.py
rage4/cli.py
rage4/rage4.py
rage4.egg-info/PKG-INFO
rage4.egg-info/SOURCES.txt
rage4.egg-info/dependency_links.txt
rage4.egg-info/entry_points.txt
rage4.egg-info/not-zip-safe
rage4.egg-info/requires.txt
rage4.egg-info/top_level.txt
tests/__init__.py
tests/test_rage4.py