Metadata-Version: 1.2
Name: rage4
Version: 0.1.0
Summary: Python Rage4 API Module
Home-page: https://github.com/ahmedbodi/rage4
Author: Ahmed Bodiwala
Author-email: ahmedbodi@crypto-expert.com
License: UNKNOWN
Keywords: rage4
Platform: UNKNOWN
Classifier: Development Status :: 2 - Pre-Alpha
Classifier: Intended Audience :: Developers
Classifier: Natural Language :: English
Classifier: Programming Language :: Python :: 3
Classifier: Programming Language :: Python :: 3.5
Classifier: Programming Language :: Python :: 3.6
Classifier: Programming Language :: Python :: 3.7
Classifier: Programming Language :: Python :: 3.8
Requires-Python: >=3.5
